rl_test_storage_handlers/__init__.py
rl_test_storage_handlers/storage_handler.py
rl_test_storage_handlers/file/__init__.py
rl_test_storage_handlers/file/file_handler.py
rl_test_storage_handlers/file/text_file_handler.py
rl_test_storage_handlers/file/params/__init__.py
rl_test_storage_handlers/file/params/file_data.py
rl_test_storage_handlers/file/params/file_destination.py
rl_test_storage_handlers/params/__init__.py
rl_test_storage_handlers/params/storage_data.py
rl_test_storage_handlers/params/storage_destination.py
rl_test_storage_handlers-0.1.4.dist-info/METADATA
rl_test_storage_handlers-0.1.4.dist-info/WHEEL
rl_test_storage_handlers-0.1.4.dist-info/top_level.txt
rl_test_storage_handlers-0.1.4.dist-info/RECORD
